[
  {
    "StartFrame": 1,
    "EndFrame": 27,
    "Info": {
      "Type": "layout",
      "Grid": {
        "Rows": 1,
        "Columns": 1,
        "Margin": 0
      },
      "Content": [
        {
          "Row": 0,
          "Column": 0,
          "Kind": "video",
          "MediaUrl": "https://test-v1.blr1.digitaloceanspaces.com/temp/workspace-f4d1b74c-b6c2-4a85-bfd1-d31f7dd89453/f53aba69-ea91-4015-8178-223fa18b5de7.webm"
        }
      ]
    },
    "PreviewUrl": "https://test-v1.blr1.digitaloceanspaces.com/temp/1-low.png"
  },
  {
    "StartFrame": 28,
    "EndFrame": 57,
    "Info": {
      "Type": "layout",
      "Grid": {
        "Rows": 0,
        "Columns": 0,
        "Margin": 0
      },
      "Content": []
    },
    "PreviewUrl": "https://test-v1.blr1.digitaloceanspaces.com/temp/28-low.png"
  },
  {
    "StartFrame": 58,
    "EndFrame": 61,
    "Info": {
      "Type": "layout",
      "Grid": {
        "Rows": 1,
        "Columns": 1,
        "Margin": 0
      },
      "Content": [
        {
          "Row": 0,
          "Column": 0,
          "Kind": "image",
          "MediaUrl": "https://test-v1.blr1.digitaloceanspaces.com/temp/workspace-f4d1b74c-b6c2-4a85-bfd1-d31f7dd89453/f89e6a65-1241-40f7-968f-d495cd1a16c0.png"
        }
      ]
    },
    "PreviewUrl": "https://test-v1.blr1.digitaloceanspaces.com/temp/58-low.png"
  },
  {
    "StartFrame": 62,
    "EndFrame": 63,
    "Info": {
      "Type": "layout",
      "Grid": {
        "Rows": 1,
        "Columns": 1,
        "Margin": 0
      },
      "Content": [
        {
          "Row": 0,
          "Column": 0,
          "Kind": "image",
          "MediaUrl": "https://test-v1.blr1.digitaloceanspaces.com/temp/workspace-f4d1b74c-b6c2-4a85-bfd1-d31f7dd89453/8666d5bd-c36e-4fc7-96ec-0d66741d0a0d.png"
        }
      ]
    },
    "PreviewUrl": "https://test-v1.blr1.digitaloceanspaces.com/temp/62-low.png"
  },
  {
    "StartFrame": 64,
    "EndFrame": 66,
    "Info": {
      "Type": "layout",
      "Grid": {
        "Rows": 1,
        "Columns": 1,
        "Margin": 0
      },
      "Content": [
        {
          "Row": 0,
          "Column": 0,
          "Kind": "image",
          "MediaUrl": "https://test-v1.blr1.digitaloceanspaces.com/temp/workspace-f4d1b74c-b6c2-4a85-bfd1-d31f7dd89453/018e2973-551e-4f7e-a15e-8ee53c8e0d47.png"
        }
      ]
    },
    "PreviewUrl": "https://test-v1.blr1.digitaloceanspaces.com/temp/64-low.png"
  },
  {
    "StartFrame": 67,
    "EndFrame": 69,
    "Info": {
      "Type": "layout",
      "Grid": {
        "Rows": 1,
        "Columns": 1,
        "Margin": 0
      },
      "Content": [
        {
          "Row": 0,
          "Column": 0,
          "Kind": "image",
          "MediaUrl": "https://test-v1.blr1.digitaloceanspaces.com/temp/workspace-f4d1b74c-b6c2-4a85-bfd1-d31f7dd89453/7be4ac37-14c9-4594-9ceb-0d6ba184eab5.png"
        }
      ]
    },
    "PreviewUrl": "https://test-v1.blr1.digitaloceanspaces.com/temp/67-low.png"
  },
  {
    "StartFrame": 70,
    "EndFrame": 72,
    "Info": {
      "Type": "layout",
      "Grid": {
        "Rows": 1,
        "Columns": 1,
        "Margin": 0
      },
      "Content": [
        {
          "Row": 0,
          "Column": 0,
          "Kind": "image",
          "MediaUrl": "https://test-v1.blr1.digitaloceanspaces.com/temp/workspace-f4d1b74c-b6c2-4a85-bfd1-d31f7dd89453/8f1d2420-23f9-4762-a28b-c8df4ba5eab8.png"
        }
      ]
    },
    "PreviewUrl": "https://test-v1.blr1.digitaloceanspaces.com/temp/70-low.png"
  },
  {
    "StartFrame": 73,
    "EndFrame": 75,
    "Info": {
      "Type": "layout",
      "Grid": {
        "Rows": 1,
        "Columns": 1,
        "Margin": 0
      },
      "Content": [
        {
          "Row": 0,
          "Column": 0,
          "Kind": "image",
          "MediaUrl": "https://test-v1.blr1.digitaloceanspaces.com/temp/workspace-f4d1b74c-b6c2-4a85-bfd1-d31f7dd89453/6dffd1fe-58f3-4cde-920d-fd37ddda13bf.png"
        }
      ]
    },
    "PreviewUrl": "https://test-v1.blr1.digitaloceanspaces.com/temp/73-low.png"
  },
  {
    "StartFrame": 76,
    "EndFrame": 78,
    "Info": {
      "Type": "layout",
      "Grid": {
        "Rows": 1,
        "Columns": 1,
        "Margin": 0
      },
      "Content": [
        {
          "Row": 0,
          "Column": 0,
          "Kind": "image",
          "MediaUrl": "https://test-v1.blr1.digitaloceanspaces.com/temp/workspace-f4d1b74c-b6c2-4a85-bfd1-d31f7dd89453/3650f848-9f1d-4f58-b41d-4e221e39a1bb.png"
        }
      ]
    },
    "PreviewUrl": "https://test-v1.blr1.digitaloceanspaces.com/temp/76-low.png"
  },
  {
    "StartFrame": 79,
    "EndFrame": 81,
    "Info": {
      "Type": "layout",
      "Grid": {
        "Rows": 1,
        "Columns": 1,
        "Margin": 0
      },
      "Content": [
        {
          "Row": 0,
          "Column": 0,
          "Kind": "image",
          "MediaUrl": "https://test-v1.blr1.digitaloceanspaces.com/temp/workspace-f4d1b74c-b6c2-4a85-bfd1-d31f7dd89453/16ad69dc-94fb-4763-b047-b63d96344222.png"
        }
      ]
    },
    "PreviewUrl": "https://test-v1.blr1.digitaloceanspaces.com/temp/79-low.png"
  },
  {
    "StartFrame": 82,
    "EndFrame": 84,
    "Info": {
      "Type": "layout",
      "Grid": {
        "Rows": 1,
        "Columns": 1,
        "Margin": 0
      },
      "Content": [
        {
          "Row": 0,
          "Column": 0,
          "Kind": "image",
          "MediaUrl": "https://test-v1.blr1.digitaloceanspaces.com/temp/workspace-f4d1b74c-b6c2-4a85-bfd1-d31f7dd89453/fe6e0b11-0356-41b1-81d9-806292050618.png"
        }
      ]
    },
    "PreviewUrl": "https://test-v1.blr1.digitaloceanspaces.com/temp/82-low.png"
  },
  {
    "StartFrame": 85,
    "EndFrame": 87,
    "Info": {
      "Type": "layout",
      "Grid": {
        "Rows": 1,
        "Columns": 1,
        "Margin": 0
      },
      "Content": [
        {
          "Row": 0,
          "Column": 0,
          "Kind": "image",
          "MediaUrl": "https://test-v1.blr1.digitaloceanspaces.com/temp/workspace-f4d1b74c-b6c2-4a85-bfd1-d31f7dd89453/366d87cd-e0b6-4260-8152-8a5c9d82b67b.png"
        }
      ]
    },
    "PreviewUrl": "https://test-v1.blr1.digitaloceanspaces.com/temp/85-low.png"
  },
  {
    "StartFrame": 88,
    "EndFrame": 90,
    "Info": {
      "Type": "layout",
      "Grid": {
        "Rows": 1,
        "Columns": 1,
        "Margin": 0
      },
      "Content": [
        {
          "Row": 0,
          "Column": 0,
          "Kind": "image",
          "MediaUrl": "https://test-v1.blr1.digitaloceanspaces.com/temp/workspace-f4d1b74c-b6c2-4a85-bfd1-d31f7dd89453/5f78a1b7-3a33-4f8b-915a-078cb5319f31.png"
        }
      ]
    },
    "PreviewUrl": "https://test-v1.blr1.digitaloceanspaces.com/temp/88-low.png"
  },
  {
    "StartFrame": 91,
    "EndFrame": 93,
    "Info": {
      "Type": "layout",
      "Grid": {
        "Rows": 1,
        "Columns": 1,
        "Margin": 0
      },
      "Content": [
        {
          "Row": 0,
          "Column": 0,
          "Kind": "image",
          "MediaUrl": "https://test-v1.blr1.digitaloceanspaces.com/temp/workspace-f4d1b74c-b6c2-4a85-bfd1-d31f7dd89453/0b20da69-61c3-4f8f-8a35-9ddc4fea38dd.png"
        }
      ]
    },
    "PreviewUrl": "https://test-v1.blr1.digitaloceanspaces.com/temp/91-low.png"
  },
  {
    "StartFrame": 94,
    "EndFrame": 96,
    "Info": {
      "Type": "layout",
      "Grid": {
        "Rows": 1,
        "Columns": 1,
        "Margin": 0
      },
      "Content": [
        {
          "Row": 0,
          "Column": 0,
          "Kind": "image",
          "MediaUrl": "https://test-v1.blr1.digitaloceanspaces.com/temp/workspace-f4d1b74c-b6c2-4a85-bfd1-d31f7dd89453/8da71da3-4477-413b-9472-da51305360aa.png"
        }
      ]
    },
    "PreviewUrl": "https://test-v1.blr1.digitaloceanspaces.com/temp/94-low.png"
  },
  {
    "StartFrame": 97,
    "EndFrame": 99,
    "Info": {
      "Type": "layout",
      "Grid": {
        "Rows": 1,
        "Columns": 1,
        "Margin": 0
      },
      "Content": [
        {
          "Row": 0,
          "Column": 0,
          "Kind": "image",
          "MediaUrl": "https://test-v1.blr1.digitaloceanspaces.com/temp/workspace-f4d1b74c-b6c2-4a85-bfd1-d31f7dd89453/03944889-dcd6-4b43-8865-819499f4676a.png"
        }
      ]
    },
    "PreviewUrl": "https://test-v1.blr1.digitaloceanspaces.com/temp/97-low.png"
  },
  {
    "StartFrame": 100,
    "EndFrame": 102,
    "Info": {
      "Type": "layout",
      "Grid": {
        "Rows": 1,
        "Columns": 1,
        "Margin": 0
      },
      "Content": [
        {
          "Row": 0,
          "Column": 0,
          "Kind": "image",
          "MediaUrl": "https://test-v1.blr1.digitaloceanspaces.com/temp/workspace-f4d1b74c-b6c2-4a85-bfd1-d31f7dd89453/882883f7-c381-4f96-96d7-85a4540ae38a.png"
        }
      ]
    },
    "PreviewUrl": "https://test-v1.blr1.digitaloceanspaces.com/temp/100-low.png"
  },
  {
    "StartFrame": 103,
    "EndFrame": 105,
    "Info": {
      "Type": "layout",
      "Grid": {
        "Rows": 1,
        "Columns": 1,
        "Margin": 0
      },
      "Content": [
        {
          "Row": 0,
          "Column": 0,
          "Kind": "image",
          "MediaUrl": "https://test-v1.blr1.digitaloceanspaces.com/temp/workspace-f4d1b74c-b6c2-4a85-bfd1-d31f7dd89453/a9b0dddd-332f-41bf-9f5f-807dcb1bed5e.png"
        }
      ]
    },
    "PreviewUrl": "https://test-v1.blr1.digitaloceanspaces.com/temp/103-low.png"
  },
  {
    "StartFrame": 106,
    "EndFrame": 108,
    "Info": {
      "Type": "layout",
      "Grid": {
        "Rows": 1,
        "Columns": 1,
        "Margin": 0
      },
      "Content": [
        {
          "Row": 0,
          "Column": 0,
          "Kind": "image",
          "MediaUrl": "https://test-v1.blr1.digitaloceanspaces.com/temp/workspace-f4d1b74c-b6c2-4a85-bfd1-d31f7dd89453/f6c2f25b-14e1-459a-882f-f2bdd95e5701.png"
        }
      ]
    },
    "PreviewUrl": "https://test-v1.blr1.digitaloceanspaces.com/temp/106-low.png"
  },
  {
    "StartFrame": 109,
    "EndFrame": 126,
    "Info": {
      "Type": "layout",
      "Grid": {
        "Rows": 1,
        "Columns": 1,
        "Margin": 0
      },
      "Content": [
        {
          "Row": 0,
          "Column": 0,
          "Kind": "video",
          "MediaUrl": "https://test-v1.blr1.digitaloceanspaces.com/temp/workspace-f4d1b74c-b6c2-4a85-bfd1-d31f7dd89453/170b8e7f-04e5-421a-8987-9b5d9cf6b9af.webm"
        }
      ]
    },
    "PreviewUrl": "https://test-v1.blr1.digitaloceanspaces.com/temp/109-low.png"
  },
  {
    "StartFrame": 127,
    "EndFrame": 172,
    "Info": {
      "Type": "layout",
      "Grid": {
        "Rows": 1,
        "Columns": 1,
        "Margin": 0
      },
      "Content": [
        {
          "Row": 0,
          "Column": 0,
          "Kind": "video",
          "MediaUrl": "https://test-v1.blr1.digitaloceanspaces.com/temp/workspace-f4d1b74c-b6c2-4a85-bfd1-d31f7dd89453/bd39d3d4-4fb9-4b3b-92de-c4bbd6ed76e5.webm"
        }
      ]
    },
    "PreviewUrl": "https://test-v1.blr1.digitaloceanspaces.com/temp/127-low.png"
  },
  {
    "StartFrame": 173,
    "EndFrame": 183,
    "Info": {
      "Type": "dissolve",
      "Grid": null,
      "Content": []
    },
    "PreviewUrl": "https://test-v1.blr1.digitaloceanspaces.com/temp/173-low.png"
  },
  {
    "StartFrame": 184,
    "EndFrame": 218,
    "Info": {
      "Type": "layout",
      "Grid": {
        "Rows": 1,
        "Columns": 1,
        "Margin": 0
      },
      "Content": [
        {
          "Row": 0,
          "Column": 0,
          "Kind": "video",
          "MediaUrl": "https://test-v1.blr1.digitaloceanspaces.com/temp/workspace-f4d1b74c-b6c2-4a85-bfd1-d31f7dd89453/27b56938-eb6f-46af-b154-849e0a81fabe.webm"
        }
      ]
    },
    "PreviewUrl": "https://test-v1.blr1.digitaloceanspaces.com/temp/184-low.png"
  },
  {
    "StartFrame": 219,
    "EndFrame": 233,
    "Info": {
      "Type": "layout",
      "Grid": {
        "Rows": 1,
        "Columns": 1,
        "Margin": 0
      },
      "Content": [
        {
          "Row": 0,
          "Column": 0,
          "Kind": "video",
          "MediaUrl": "https://test-v1.blr1.digitaloceanspaces.com/temp/workspace-f4d1b74c-b6c2-4a85-bfd1-d31f7dd89453/7aff083d-2328-45bf-9582-c6b987968053.webm"
        }
      ]
    },
    "PreviewUrl": "https://test-v1.blr1.digitaloceanspaces.com/temp/219-low.png"
  },
  {
    "StartFrame": 234,
    "EndFrame": 246,
    "Info": {
      "Type": "layout",
      "Grid": {
        "Rows": 1,
        "Columns": 1,
        "Margin": 0
      },
      "Content": [
        {
          "Row": 0,
          "Column": 0,
          "Kind": "video",
          "MediaUrl": "https://test-v1.blr1.digitaloceanspaces.com/temp/workspace-f4d1b74c-b6c2-4a85-bfd1-d31f7dd89453/87a69ec6-1cf1-43be-ae28-f46b4a16e840.webm"
        }
      ]
    },
    "PreviewUrl": "https://test-v1.blr1.digitaloceanspaces.com/temp/234-low.png"
  },
  {
    "StartFrame": 247,
    "EndFrame": 258,
    "Info": {
      "Type": "layout",
      "Grid": {
        "Rows": 1,
        "Columns": 1,
        "Margin": 0
      },
      "Content": [
        {
          "Row": 0,
          "Column": 0,
          "Kind": "video",
          "MediaUrl": "https://test-v1.blr1.digitaloceanspaces.com/temp/workspace-f4d1b74c-b6c2-4a85-bfd1-d31f7dd89453/390ad43c-8605-4146-9474-a323796c4ee4.webm"
        }
      ]
    },
    "PreviewUrl": "https://test-v1.blr1.digitaloceanspaces.com/temp/247-low.png"
  },
  {
    "StartFrame": 259,
    "EndFrame": 272,
    "Info": {
      "Type": "layout",
      "Grid": {
        "Rows": 1,
        "Columns": 1,
        "Margin": 0
      },
      "Content": [
        {
          "Row": 0,
          "Column": 0,
          "Kind": "video",
          "MediaUrl": "https://test-v1.blr1.digitaloceanspaces.com/temp/workspace-f4d1b74c-b6c2-4a85-bfd1-d31f7dd89453/b17c8feb-a295-4617-829d-17e94731d836.webm"
        }
      ]
    },
    "PreviewUrl": "https://test-v1.blr1.digitaloceanspaces.com/temp/259-low.png"
  },
  {
    "StartFrame": 273,
    "EndFrame": 285,
    "Info": {
      "Type": "layout",
      "Grid": {
        "Rows": 1,
        "Columns": 1,
        "Margin": 0
      },
      "Content": [
        {
          "Row": 0,
          "Column": 0,
          "Kind": "video",
          "MediaUrl": "https://test-v1.blr1.digitaloceanspaces.com/temp/workspace-f4d1b74c-b6c2-4a85-bfd1-d31f7dd89453/25aa15d2-4a96-4350-8a50-b82e6900f56e.webm"
        }
      ]
    },
    "PreviewUrl": "https://test-v1.blr1.digitaloceanspaces.com/temp/273-low.png"
  },
  {
    "StartFrame": 286,
    "EndFrame": 299,
    "Info": {
      "Type": "layout",
      "Grid": {
        "Rows": 1,
        "Columns": 1,
        "Margin": 0
      },
      "Content": [
        {
          "Row": 0,
          "Column": 0,
          "Kind": "video",
          "MediaUrl": "https://test-v1.blr1.digitaloceanspaces.com/temp/workspace-f4d1b74c-b6c2-4a85-bfd1-d31f7dd89453/53d74156-1df3-454d-9a1b-f5a90f95a7b5.webm"
        }
      ]
    },
    "PreviewUrl": "https://test-v1.blr1.digitaloceanspaces.com/temp/286-low.png"
  },
  {
    "StartFrame": 300,
    "EndFrame": 312,
    "Info": {
      "Type": "layout",
      "Grid": {
        "Rows": 1,
        "Columns": 1,
        "Margin": 0
      },
      "Content": [
        {
          "Row": 0,
          "Column": 0,
          "Kind": "video",
          "MediaUrl": "https://test-v1.blr1.digitaloceanspaces.com/temp/workspace-f4d1b74c-b6c2-4a85-bfd1-d31f7dd89453/cc0dd5f4-29ce-4454-8d4d-40c223c8b790.webm"
        }
      ]
    },
    "PreviewUrl": "https://test-v1.blr1.digitaloceanspaces.com/temp/300-low.png"
  },
  {
    "StartFrame": 313,
    "EndFrame": 326,
    "Info": {
      "Type": "layout",
      "Grid": {
        "Rows": 1,
        "Columns": 1,
        "Margin": 0
      },
      "Content": [
        {
          "Row": 0,
          "Column": 0,
          "Kind": "video",
          "MediaUrl": "https://test-v1.blr1.digitaloceanspaces.com/temp/workspace-f4d1b74c-b6c2-4a85-bfd1-d31f7dd89453/c2108980-bb29-45be-b750-739aa1493087.webm"
        }
      ]
    },
    "PreviewUrl": "https://test-v1.blr1.digitaloceanspaces.com/temp/313-low.png"
  },
  {
    "StartFrame": 327,
    "EndFrame": 341,
    "Info": {
      "Type": "layout",
      "Grid": {
        "Rows": 3,
        "Columns": 1,
        "Margin": 0.18
      },
      "Content": [
        {
          "Row": 0,
          "Column": 0,
          "Kind": "image",
          "MediaUrl": "https://test-v1.blr1.digitaloceanspaces.com/temp/workspace-f4d1b74c-b6c2-4a85-bfd1-d31f7dd89453/96464d6e-3157-4fdd-baea-cb87d3734672.png"
        },
        {
          "Row": 1,
          "Column": 0,
          "Kind": "empty",
          "MediaUrl": ""
        },
        {
          "Row": 2,
          "Column": 0,
          "Kind": "empty",
          "MediaUrl": ""
        }
      ]
    },
    "PreviewUrl": "https://test-v1.blr1.digitaloceanspaces.com/temp/327-low.png"
  },
  {
    "StartFrame": 342,
    "EndFrame": 353,
    "Info": {
      "Type": "layout",
      "Grid": {
        "Rows": 3,
        "Columns": 1,
        "Margin": 0.18
      },
      "Content": [
        {
          "Row": 0,
          "Column": 0,
          "Kind": "image",
          "MediaUrl": "https://test-v1.blr1.digitaloceanspaces.com/temp/workspace-f4d1b74c-b6c2-4a85-bfd1-d31f7dd89453/66b8aadd-f0ec-4c70-ae2c-0526711e5c7c.png"
        },
        {
          "Row": 1,
          "Column": 0,
          "Kind": "image",
          "MediaUrl": "https://test-v1.blr1.digitaloceanspaces.com/temp/workspace-f4d1b74c-b6c2-4a85-bfd1-d31f7dd89453/41e0c6fd-535e-42de-8101-168c6a475c98.png"
        },
        {
          "Row": 2,
          "Column": 0,
          "Kind": "empty",
          "MediaUrl": ""
        }
      ]
    },
    "PreviewUrl": "https://test-v1.blr1.digitaloceanspaces.com/temp/342-low.png"
  },
  {
    "StartFrame": 354,
    "EndFrame": 363,
    "Info": {
      "Type": "layout",
      "Grid": {
        "Rows": 3,
        "Columns": 1,
        "Margin": 0.18
      },
      "Content": [
        {
          "Row": 0,
          "Column": 0,
          "Kind": "image",
          "MediaUrl": "https://test-v1.blr1.digitaloceanspaces.com/temp/workspace-f4d1b74c-b6c2-4a85-bfd1-d31f7dd89453/3a181236-d38c-4dd1-9c72-d3eec1b4358e.png"
        },
        {
          "Row": 1,
          "Column": 0,
          "Kind": "image",
          "MediaUrl": "https://test-v1.blr1.digitaloceanspaces.com/temp/workspace-f4d1b74c-b6c2-4a85-bfd1-d31f7dd89453/83161bb5-e8db-4085-91b2-ef0228fd0aa5.png"
        },
        {
          "Row": 2,
          "Column": 0,
          "Kind": "image",
          "MediaUrl": "https://test-v1.blr1.digitaloceanspaces.com/temp/workspace-f4d1b74c-b6c2-4a85-bfd1-d31f7dd89453/107cecf2-ca47-4446-b3f0-44702c82413b.png"
        }
      ]
    },
    "PreviewUrl": "https://test-v1.blr1.digitaloceanspaces.com/temp/354-low.png"
  },
  {
    "StartFrame": 364,
    "EndFrame": 378,
    "Info": {
      "Type": "layout",
      "Grid": {
        "Rows": 3,
        "Columns": 1,
        "Margin": 0
      },
      "Content": [
        {
          "Row": 0,
          "Column": 0,
          "Kind": "video",
          "MediaUrl": "https://test-v1.blr1.digitaloceanspaces.com/temp/workspace-f4d1b74c-b6c2-4a85-bfd1-d31f7dd89453/11f94320-a0a5-4c47-9843-ef5781b42e10.webm"
        },
        {
          "Row": 1,
          "Column": 0,
          "Kind": "image",
          "MediaUrl": "https://test-v1.blr1.digitaloceanspaces.com/temp/workspace-f4d1b74c-b6c2-4a85-bfd1-d31f7dd89453/db22b73f-58dc-476f-9bef-ff253d562988.png"
        },
        {
          "Row": 2,
          "Column": 0,
          "Kind": "image",
          "MediaUrl": "https://test-v1.blr1.digitaloceanspaces.com/temp/workspace-f4d1b74c-b6c2-4a85-bfd1-d31f7dd89453/aed7a3b6-0d19-463e-bc42-d9720444b841.png"
        }
      ]
    },
    "PreviewUrl": "https://test-v1.blr1.digitaloceanspaces.com/temp/364-low.png"
  },
  {
    "StartFrame": 379,
    "EndFrame": 392,
    "Info": {
      "Type": "layout",
      "Grid": {
        "Rows": 3,
        "Columns": 1,
        "Margin": 0.18
      },
      "Content": [
        {
          "Row": 0,
          "Column": 0,
          "Kind": "video",
          "MediaUrl": "https://test-v1.blr1.digitaloceanspaces.com/temp/workspace-f4d1b74c-b6c2-4a85-bfd1-d31f7dd89453/1cb34177-83c2-4499-aa23-3367b0ed976b.webm"
        },
        {
          "Row": 1,
          "Column": 0,
          "Kind": "video",
          "MediaUrl": "https://test-v1.blr1.digitaloceanspaces.com/temp/workspace-f4d1b74c-b6c2-4a85-bfd1-d31f7dd89453/72e6e994-b897-441c-8422-1b278e8b30a8.webm"
        },
        {
          "Row": 2,
          "Column": 0,
          "Kind": "image",
          "MediaUrl": "https://test-v1.blr1.digitaloceanspaces.com/temp/workspace-f4d1b74c-b6c2-4a85-bfd1-d31f7dd89453/85118489-c15e-40f3-a5ef-714056874139.png"
        }
      ]
    },
    "PreviewUrl": "https://test-v1.blr1.digitaloceanspaces.com/temp/379-low.png"
  },
  {
    "StartFrame": 393,
    "EndFrame": 422,
    "Info": {
      "Type": "layout",
      "Grid": {
        "Rows": 3,
        "Columns": 1,
        "Margin": 0.18
      },
      "Content": [
        {
          "Row": 0,
          "Column": 0,
          "Kind": "video",
          "MediaUrl": "https://test-v1.blr1.digitaloceanspaces.com/temp/workspace-f4d1b74c-b6c2-4a85-bfd1-d31f7dd89453/4b12fbd9-e019-408e-b952-60c9e95d6af7.webm"
        },
        {
          "Row": 1,
          "Column": 0,
          "Kind": "video",
          "MediaUrl": "https://test-v1.blr1.digitaloceanspaces.com/temp/workspace-f4d1b74c-b6c2-4a85-bfd1-d31f7dd89453/1dc946d1-0485-433a-8b36-dbbf2172f44a.webm"
        },
        {
          "Row": 2,
          "Column": 0,
          "Kind": "video",
          "MediaUrl": "https://test-v1.blr1.digitaloceanspaces.com/temp/workspace-f4d1b74c-b6c2-4a85-bfd1-d31f7dd89453/a342004f-c8b3-45f4-88bc-10953cbebf59.webm"
        }
      ]
    },
    "PreviewUrl": "https://test-v1.blr1.digitaloceanspaces.com/temp/393-low.png"
  }
]
